FastOptDict/FastOptDict.py
FastOptDict/__init__.py
FastOptDict-1.0.0.dist-info/METADATA
FastOptDict-1.0.0.dist-info/WHEEL
FastOptDict-1.0.0.dist-info/top_level.txt
FastOptDict-1.0.0.dist-info/RECORD
