Metadata-Version: 2.1
Name: FastOptDict
Version: 1.0.0
Summary: A package for operating
Home-page: https://github.com/JulianZackWu/FastOptDict
Author: JulianZackWu
Author-email: julianzackwu@gmail.com
Classifier: Programming Language :: Python :: 3
Classifier: License :: OSI Approved :: MIT License
Classifier: Operating System :: OS Independent
